nixbot/brokers.py
nixbot/clients.py
nixbot/command.py
nixbot/configs.py
nixbot/defines.py
nixbot/handler.py
nixbot/loggers.py
nixbot/message.py
nixbot/methods.py
nixbot/objects.py
nixbot/persist.py
nixbot/repeats.py
nixbot/serials.py
nixbot/statics.py
nixbot/threads.py
nixbot/timings.py
nixbot/utility.py
nixbot/workdir.py
nixbot/modules/__init__.py
nixbot/modules/atr.py
nixbot/modules/flt.py
nixbot/modules/fnd.py
nixbot/modules/irc.py
nixbot/modules/log.py
nixbot/modules/lst.py
nixbot/modules/man.py
nixbot/modules/mbx.py
nixbot/modules/mdl.py
nixbot/modules/pth.py
nixbot/modules/req.py
nixbot/modules/rss.py
nixbot/modules/rst.py
nixbot/modules/sil.py
nixbot/modules/slg.py
nixbot/modules/tdo.py
nixbot/modules/thr.py
nixbot/modules/tmr.py
nixbot/modules/udp.py
nixbot/modules/upt.py
nixbot/modules/web.py
nixbot/modules/wsd.py
nixbot/network/__init__.py
nixbot/nucleus/__init__.py
nixbot-180.data/scripts/nixbot
nixbot-180.dist-info/METADATA
nixbot-180.dist-info/WHEEL
nixbot-180.dist-info/top_level.txt
nixbot-180.dist-info/RECORD
