Metadata-Version: 2.4
Name: nixbot
Version: 180
Summary: NIXBOT
Author-email: Bart Thate <nixtniet@gmail.com>
License-Expression: Unlicense
Project-URL: home, https://pypi.org/project/nixbot
Project-URL: bugs, https://github.com/nixtniet/nixbot/issues
Project-URL: source, https://github.com/nixtniet/nixbot
Classifier: Development Status :: 3 - Alpha
Classifier: Operating System :: Unix
Classifier: Programming Language :: Python :: 3
Classifier: Topic :: Utilities
